pyvolt/__init__.py
pyvolt/measurement.py
pyvolt/network.py
pyvolt/nv_powerflow.py
pyvolt/nv_state_estimator.py
pyvolt/results.py
pyvolt-0.2.dist-info/LICENSE
pyvolt-0.2.dist-info/METADATA
pyvolt-0.2.dist-info/WHEEL
pyvolt-0.2.dist-info/top_level.txt
pyvolt-0.2.dist-info/RECORD
