Metadata-Version: 1.0
Name: pyvolt
Version: 0.2
Summary: State Estimation
Home-page: UNKNOWN
Author: Marco Pau, Markus Mirz, Jan Dinkelbach
Author-email: acs-software@eonerc.rwth-aachen.de
License: UNKNOWN
Platform: UNKNOWN
